spicemix/__init__.py
spicemix/analysis.py
spicemix/components.py
spicemix/estimate_parameters.py
spicemix/estimate_weights.py
spicemix/initialization.py
spicemix/io.py
spicemix/main.py
spicemix/model.py
spicemix/sample_for_integral.py
spicemix/simulation_framework.py
spicemix/synthesize.py
spicemix/util.py
spicemix-0.0.1.dist-info/METADATA
spicemix-0.0.1.dist-info/WHEEL
spicemix-0.0.1.dist-info/licenses/LICENSE
spicemix-0.0.1.dist-info/RECORD
