Metadata-Version: 2.1
Name: spicemix
Version: 0.0.1
Summary: SpiceMix: a probabilistic graphical model for spatial transcriptomics data
Project-URL: Homepage, https://github.com/pypa/sampleproject
Project-URL: Bug Tracker, https://github.com/pypa/sampleproject/issues
Author-email: Shahul Alam <alam.shahul@gmail.com.com>
License: MIT License
Classifier: License :: OSI Approved :: MIT License
Classifier: Operating System :: OS Independent
Classifier: Programming Language :: Python :: 3
Requires-Python: >=3.7
Requires-Dist: anndata>=0.8.0
Requires-Dist: matplotlib>=3.3.4
Requires-Dist: numpy>=1.20.1
Requires-Dist: pandas>=1.2.4
Requires-Dist: scanpy>=1.8.1
Requires-Dist: scikit-learn>=0.24.1
Requires-Dist: scipy>=1.7.1
Requires-Dist: seaborn>=0.11.1
Requires-Dist: squidpy>=1.2.2
Requires-Dist: torch>=1.10.1+cu113
Requires-Dist: tqdm>=4.60.0
Requires-Dist: umap-learn>=0.5.1
